setup.cfg
setup.py
angular_scaffold/__init__.py
angular_scaffold/_docs.py
angular_scaffold/_version.py
angular_scaffold/management/__init__.py
angular_scaffold/management/commands/__init__.py
angular_scaffold/management/commands/addroute.py
angular_scaffold/management/commands/createcsrf.py
angular_scaffold/management/commands/createdebugger.py
angular_scaffold/management/commands/createlimiter.py
angular_scaffold/management/commands/generatedocs.py
angular_scaffold/management/commands/scaffold.py
angular_scaffold/management/commands/startcontroller.py
angular_scaffold/management/commands/startroutes.py
angular_scaffold/management/commands/startservice.py
angular_scaffold/management/commands/startview.py
angular_scaffold/management/commands/helpers/__init__.py
angular_scaffold/management/commands/helpers/_add_route.py
angular_scaffold/management/commands/helpers/_generate_assets.py
angular_scaffold/management/commands/helpers/_generate_controller.py
angular_scaffold/management/commands/helpers/_generate_csrf.py
angular_scaffold/management/commands/helpers/_generate_debugger.py
angular_scaffold/management/commands/helpers/_generate_docs.py
angular_scaffold/management/commands/helpers/_generate_limiter.py
angular_scaffold/management/commands/helpers/_generate_routes.py
angular_scaffold/management/commands/helpers/_generate_service.py
angular_scaffold/management/commands/helpers/_generate_view.py
angular_scaffold/management/commands/helpers/_update_dependencies.py
django_angular_scaffold.egg-info/PKG-INFO
django_angular_scaffold.egg-info/SOURCES.txt
django_angular_scaffold.egg-info/dependency_links.txt
django_angular_scaffold.egg-info/top_level.txt