Metadata-Version: 1.1
Name: django-angular-scaffold
Version: 0.11.3
Summary: AngularJS Scaffolding for Django
Home-page: https://github.com/mc706/django-angular-scaffold
Author: Ryan McDevitt
Author-email: mcdevitt.ryan@gmail.com
License: MIT License
Download-URL: https://github.com/mc706/django-angular-scaffold/tarball/0.11
Keywords: django,angular,scaffold
Platform: UNKNOWN
